README.txt
setup.cfg
setup.py
docs/HISTORY.txt
docs/LICENSE.GPL
docs/LICENSE.txt
docs/MANUAL.txt
raptus/__init__.py
raptus.article.header.egg-info/PKG-INFO
raptus.article.header.egg-info/SOURCES.txt
raptus.article.header.egg-info/dependency_links.txt
raptus.article.header.egg-info/entry_points.txt
raptus.article.header.egg-info/namespace_packages.txt
raptus.article.header.egg-info/not-zip-safe
raptus.article.header.egg-info/requires.txt
raptus.article.header.egg-info/top_level.txt
raptus/article/__init__.py
raptus/article/header/__init__.py
raptus/article/header/configure.zcml
raptus/article/header/profiles/default/metadata.xml
raptus/article/header/profiles/default/types.xml
raptus/article/header/profiles/default/types/Article.xml