Metadata-Version: 1.0
Name: raptus.article.header
Version: 2.0b3
Summary: Provides header image support by integrating raptus.header in article
Home-page: http://raptus.com
Author: Raptus Ag
Author-email: dev@raptus.com
License: GPL
Platform: UNKNOWN
Classifier: Programming Language :: Python
